uk_mod_check/__init__.py
uk_mod_check/data_parser.py
uk_mod_check/data/subs.txt
uk_mod_check/data/weights.txt
uk_mod_check-1.0.dist-info/LICENSE.md
uk_mod_check-1.0.dist-info/METADATA
uk_mod_check-1.0.dist-info/WHEEL
uk_mod_check-1.0.dist-info/top_level.txt
uk_mod_check-1.0.dist-info/RECORD
