Metadata-Version: 2.1
Name: uk-mod-check
Version: 1.0
Summary: UNKNOWN
Home-page: https://github.com/as207960/uk-mod-check
Author: Q 🦄
Author-email: q@magicalcodewit.ch
License: MIT
Platform: UNKNOWN
